<PAMDataset>
  <PAMRasterBand band="1">
    <NoDataValue>-9999</NoDataValue>
    <Metadata>
      <MDI key="STATISTICS_MINIMUM">-1.8290</MDI>
      <MDI key="STATISTICS_MAXIMUM">29.6905</MDI>
      <MDI key="STATISTICS_MEAN">14.6408</MDI>
      <MDI key="STATISTICS_STDDEV">5.0400</MDI>
      <MDI key="STATISTICS_NNULL">       0</MDI>
      <MDI key="STATISTICS_NULL_PERCENT">       0</MDI>
      <MDI key="STATISTICS_NVALID">  481626</MDI>
      <MDI key="STATISTICS_VALID_PERCENT">.55200371</MDI>
    </Metadata>
  </PAMRasterBand>
</PAMDataset>
